{
    "username": "Mozilla/5.0 (Windows NT 10.0; Win64; x64) AppleWebKit/537.36 (KHTML, like Gecko) Chrome/120.0.0.0 Safari/537.36",
    "date": "2024-07-21T10:33:38.303Z",
    "measurements": {
        "crownDiameter": 12.112876230237337,
        "stemDiameter": [
            0.5179404041285453,
            0.512600224067781,
            0.5110264627929769,
            0.5104412607087553,
            0.5170968310643295,
            0.529413252040168,
            0.544486533259202
        ],
        "height": 15.070002562999989,
        "measuredHeight": [
            0.7,
            0.775,
            0.85,
            0.925,
            1.0,
            1.075,
            1.15
        ]
    }
}